{
  "version": "v1",
  "updatedAt": "2026-04-26",
  "source": "local-versioned-json",
  "region": "default",
  "years": {
    "2026": {
      "year": 2026,
      "minimumWage": 15066904,
      "taxExemption": 40000000,
      "insuranceRate": 0.07,
      "housingAllowance": 3000000,
      "foodAllowance": 2200000,
      "transportationAllowance": 1500000,
      "childAllowance": 1662555,
      "marriageAllowance": 500000,
      "seniorityAllowance": 500000,
      "taxBrackets": [
        { "upTo": 40000000, "rate": 0 },
        { "upTo": 50000000, "rate": 0.1 },
        { "upTo": 66666667, "rate": 0.15 },
        { "upTo": 100000000, "rate": 0.2 },
        { "upTo": 133333333, "rate": 0.25 },
        { "upTo": null, "rate": 0.3 }
      ]
    }
  }
}
